cups_notify/__init__.py
cups_notify/event.py
cups_notify/listener.py
cups_notify/subscriber.py
pycups_notify-0.0.6.dist-info/LICENSE
pycups_notify-0.0.6.dist-info/METADATA
pycups_notify-0.0.6.dist-info/WHEEL
pycups_notify-0.0.6.dist-info/entry_points.txt
pycups_notify-0.0.6.dist-info/top_level.txt
pycups_notify-0.0.6.dist-info/RECORD
