Metadata-Version: 2.1
Name: pycups-notify
Version: 0.0.6
Summary: Notification system for the pycups library.
Home-page: https://github.com/anxuae/pycups-notify
Author: Antoine Rousseaux
License: MIT license
Download-URL: https://github.com/anxuae/pycups-notify/archive/0.0.6.tar.gz
Keywords: printer,CUPS
Platform: unix
Platform: linux
Platform: darwin
Platform: win32
Classifier: Development Status :: 5 - Production/Stable
Classifier: Environment :: Other Environment
Classifier: Intended Audience :: Developers
Classifier: License :: OSI Approved :: MIT License
Classifier: Operating System :: POSIX :: Linux
Classifier: Programming Language :: Python :: 2.7
Classifier: Programming Language :: Python :: 3.4
Classifier: Programming Language :: Python :: 3.5
Classifier: Natural Language :: English
Classifier: Topic :: Printing
License-File: LICENSE
Requires-Dist: pycups (>=1.9.73)
